linearsvc/__init__.py
linearsvc/data/linearsvc
linearsvc-1.0.1.dist-info/LICENSE
linearsvc-1.0.1.dist-info/METADATA
linearsvc-1.0.1.dist-info/WHEEL
linearsvc-1.0.1.dist-info/top_level.txt
linearsvc-1.0.1.dist-info/RECORD
