Metadata-Version: 2.1
Name: linearsvc
Version: 1.0.1
Summary: A svm classifier model for predicting license short_name
Author: Sushant Kumar
Author-email: sushantmishra02102002@gmail.com
Requires-Python: >=3.5
License-File: LICENSE
